flask_nofloc.py
Flask_NoFLoC-1.0.0.dist-info/LICENSE
Flask_NoFLoC-1.0.0.dist-info/METADATA
Flask_NoFLoC-1.0.0.dist-info/WHEEL
Flask_NoFLoC-1.0.0.dist-info/top_level.txt
Flask_NoFLoC-1.0.0.dist-info/RECORD
