Metadata-Version: 2.1
Name: Flask-NoFLoC
Version: 1.0.0
Summary: Flask-NoFLoC sends the header      Permissions-Policy: interest-cohort=()  with each request to opt websites out of FLoC. See     https://plausible.io/blog/google-floc#how-to-opt-out-of-floc-as-a-web-developer-set-a-permissions-policy for more information. 
Home-page: https://github.com/shoeffner/Flask-NoFLoC
Author: Sebatian Höffner
Author-email: info@sebastian-hoeffner.de
License: MIT
Download-URL: https://github.com/shoeffner/Flask-NoFLoC/tarball/1.0.0
Keywords: flask,floc,nofloc
Platform: any
Classifier: Environment :: Web Environment
Classifier: Intended Audience :: Developers
Classifier: License :: OSI Approved :: MIT License
Classifier: Operating System :: OS Independent
Classifier: Programming Language :: Python
Classifier: Topic :: Internet :: WWW/HTTP :: Dynamic Content
Classifier: Topic :: Software Development :: Libraries :: Python Modules
Requires-Python: >= 3.6
Requires-Dist: Flask
Provides-Extra: docs
Requires-Dist: sphinx ; extra == 'docs'
Requires-Dist: pallets-sphinx-themes ; extra == 'docs'
Provides-Extra: pub
Requires-Dist: wheel ; extra == 'pub'
Requires-Dist: twine ; extra == 'pub'
Provides-Extra: test
Requires-Dist: pytest ; extra == 'test'
